stv_create_file/main.py
stv_create_file/core/FileCreator.py
stv_create_file/core/__init__.py
stv_create_file/core/stv_parse.py
stv_create_file/mul_lang/__init__.py
stv_create_file/mul_lang/change_text.py
stv_create_file/utils/GetConfig.py
stv_create_file/utils/__init__.py
stv_create_file/utils/utils.py
stv_create_file-0.0.5.dist-info/METADATA
stv_create_file-0.0.5.dist-info/WHEEL
stv_create_file-0.0.5.dist-info/entry_points.txt
stv_create_file-0.0.5.dist-info/top_level.txt
stv_create_file-0.0.5.dist-info/RECORD
