Metadata-Version: 2.4
Name: stv_create_file
Version: 0.0.5
Summary: Create New File with Customize Encoding
Author-email: "星灿长风v(StarWindv)" <starwindv.stv@gmail.com>
License: MIT
Project-URL: Homepage, https://github.com/StarWindv/CreateFile-with-DesignatedEncoding
Classifier: Programming Language :: Python :: 3
Requires-Python: >=3.7
Requires-Dist: chardet
Requires-Dist: stv_utils
